sopel_ipython/__init__.py
sopel_ipython-0.1.0.dist-info/LICENSE
sopel_ipython-0.1.0.dist-info/METADATA
sopel_ipython-0.1.0.dist-info/WHEEL
sopel_ipython-0.1.0.dist-info/entry_points.txt
sopel_ipython-0.1.0.dist-info/top_level.txt
sopel_ipython-0.1.0.dist-info/RECORD
