Metadata-Version: 2.1
Name: sopel-ipython
Version: 0.1.0
Summary: IPython console plugin for Sopel IRC bots
Author-email: dgw <dgw@technobabbl.es>
License: EFL-2.0
Project-URL: Homepage, https://github.com/sopel-irc/sopel-ipython
Project-URL: Bug Tracker, https://github.com/sopel-irc/sopel-ipython/issues
Keywords: sopel,plugin,bot,irc
Platform: Linux x86, x86-64
Classifier: Development Status :: 5 - Production/Stable
Classifier: Intended Audience :: Developers
Classifier: Intended Audience :: System Administrators
Classifier: License :: Eiffel Forum License (EFL)
Classifier: License :: OSI Approved :: Eiffel Forum License
Classifier: Operating System :: POSIX :: Linux
Classifier: Programming Language :: Python :: 3.8
Classifier: Programming Language :: Python :: 3.9
Classifier: Programming Language :: Python :: 3.10
Classifier: Programming Language :: Python :: 3.11
Classifier: Programming Language :: Python :: 3.12
Classifier: Topic :: Communications :: Chat :: Internet Relay Chat
Requires-Python: <4,>=3.8
License-File: LICENSE
Requires-Dist: sopel >=8.0.0.dev0
Requires-Dist: ipython >=8.0
